pyvcloud/__init__.py
pyvcloud/system_test_framework/__init__.py
pyvcloud/system_test_framework/api_base_test.py
pyvcloud/system_test_framework/base_test.py
pyvcloud/system_test_framework/depends.py
pyvcloud/system_test_framework/environment.py
pyvcloud/system_test_framework/utils.py
pyvcloud/system_test_framework/vapp_constants.py
pyvcloud/system_test_framework/constants/__init__.py
pyvcloud/system_test_framework/constants/gateway_constants.py
pyvcloud/system_test_framework/constants/ovdc_network_constant.py
pyvcloud/vcd/__init__.py
pyvcloud/vcd/acl.py
pyvcloud/vcd/amqp.py
pyvcloud/vcd/api_extension.py
pyvcloud/vcd/api_helper.py
pyvcloud/vcd/certificate.py
pyvcloud/vcd/client.py
pyvcloud/vcd/crl.py
pyvcloud/vcd/dhcp_binding.py
pyvcloud/vcd/dhcp_pool.py
pyvcloud/vcd/exceptions.py
pyvcloud/vcd/extension.py
pyvcloud/vcd/external_network.py
pyvcloud/vcd/firewall_rule.py
pyvcloud/vcd/gateway.py
pyvcloud/vcd/gateway_services.py
pyvcloud/vcd/ipsec_vpn.py
pyvcloud/vcd/metadata.py
pyvcloud/vcd/nat_rule.py
pyvcloud/vcd/network_url_constants.py
pyvcloud/vcd/nsxt_extension.py
pyvcloud/vcd/org.py
pyvcloud/vcd/platform.py
pyvcloud/vcd/pvdc.py
pyvcloud/vcd/role.py
pyvcloud/vcd/static_route.py
pyvcloud/vcd/system.py
pyvcloud/vcd/task.py
pyvcloud/vcd/test.py
pyvcloud/vcd/utils.py
pyvcloud/vcd/vapp.py
pyvcloud/vcd/vapp_dhcp.py
pyvcloud/vcd/vapp_firewall.py
pyvcloud/vcd/vapp_nat.py
pyvcloud/vcd/vapp_services.py
pyvcloud/vcd/vapp_static_route.py
pyvcloud/vcd/vcd_api_version.py
pyvcloud/vcd/vcd_client.py
pyvcloud/vcd/vdc.py
pyvcloud/vcd/vdc_network.py
pyvcloud/vcd/vm.py
pyvcloud-23.0.4.data/data/open_source_license_pyvCloud_20.0.0_GA.txt
pyvcloud-23.0.4.dist-info/AUTHORS
pyvcloud-23.0.4.dist-info/LICENSE.txt
pyvcloud-23.0.4.dist-info/METADATA
pyvcloud-23.0.4.dist-info/NOTICE.txt
pyvcloud-23.0.4.dist-info/WHEEL
pyvcloud-23.0.4.dist-info/pbr.json
pyvcloud-23.0.4.dist-info/top_level.txt
pyvcloud-23.0.4.dist-info/RECORD
