Metadata-Version: 2.1
Name: pyvcloud
Version: 23.0.4
Summary: VMware vCloud Director Python SDK
Home-page: https://github.com/vmware/pyvcloud
Author: Paco Gomez
Author-email: pgomez@vmware.com
License: Apache 2
Classifier: Environment :: Console
Classifier: Intended Audience :: System Administrators
Classifier: Intended Audience :: Developers
Classifier: Operating System :: POSIX :: Linux
Classifier: Operating System :: MacOS :: MacOS X
Classifier: Operating System :: Microsoft :: Windows
Classifier: Programming Language :: Python
Classifier: Programming Language :: Python :: 3
Requires-Python: >=3
License-File: LICENSE.txt
License-File: NOTICE.txt
License-File: AUTHORS
Requires-Dist: humanfriendly (>=4.8)
Requires-Dist: lxml (>=4.2.1)
Requires-Dist: packaging (>=21.0)
Requires-Dist: pygments (>=2.2.0)
Requires-Dist: PyYAML (>=4.2b1)
Requires-Dist: requests (>=2.18.4)
Requires-Dist: unittest-xml-reporting (>=2.2.1)
Requires-Dist: python-dateutil (>=2.8.1)
Requires-Dist: vcd-api-schemas-type (>=9.1.2.dev10)
